{
  "version": "7",
  "dialect": "mysql",
  "entries": [
    {
      "idx": 0,
      "version": "5",
      "when": 1746435465604,
      "tag": "0000_romantic_the_captain",
      "breakpoints": true
    },
    {
      "idx": 1,
      "version": "5",
      "when": 1746437646748,
      "tag": "0001_square_crusher_hogan",
      "breakpoints": true
    },
    {
      "idx": 2,
      "version": "5",
      "when": 1746541298272,
      "tag": "0002_bumpy_the_phantom",
      "breakpoints": true
    },
    {
      "idx": 3,
      "version": "5",
      "when": 1746541806140,
      "tag": "0003_flat_ogun",
      "breakpoints": true
    },
    {
      "idx": 4,
      "version": "5",
      "when": 1746542367644,
      "tag": "0004_lovely_marvel_zombies",
      "breakpoints": true
    }
  ]
}